jenkins_publisher_bitbucket/__init__.py
jenkins_publisher_bitbucket/bitbucket.py
jenkins_publisher_bitbucket-0.0.2.dist-info/entry_points.txt
jenkins_publisher_bitbucket-0.0.2.dist-info/metadata.json
jenkins_publisher_bitbucket-0.0.2.dist-info/WHEEL
jenkins_publisher_bitbucket-0.0.2.dist-info/DESCRIPTION.rst
jenkins_publisher_bitbucket-0.0.2.dist-info/top_level.txt
jenkins_publisher_bitbucket-0.0.2.dist-info/METADATA
jenkins_publisher_bitbucket-0.0.2.dist-info/RECORD
