Metadata-Version: 1.1
Name: jenkins-publisher-bitbucket
Version: 0.0.2
Summary: Jenkins Job Builder Bitbucket Notifier
Home-page: https://github.com/bobtfish/jenkins-publisher-bitbucket
Author: Tomas Doran
Author-email: bobtfish@bobtfish.net
License: MIT license
Platform: UNKNOWN
Classifier: Environment :: Console
Classifier: Intended Audience :: Developers
Classifier: Intended Audience :: Information Technology
Classifier: License :: OSI Approved :: Apache Software License
Classifier: Operating System :: OS Independent
Classifier: Programming Language :: Python
Classifier: Programming Language :: Python :: 2
Classifier: Programming Language :: Python :: 3
